nifconverter/__init__.py
nifconverter/auto_converter.py
nifconverter/cli.py
nifconverter/dbpedia.py
nifconverter/dbpedia_samething.py
nifconverter/dbpedia_sparql.py
nifconverter/settings.py
nifconverter/translator.py
nifconverter/uriconverter.py
nifconverter/utils.py
nifconverter/tests/__init__.py
nifconverter/tests/dbpedia_bases.py
nifconverter/tests/test_cli.py
nifconverter/tests/test_dbpedia.py
nifconverter/tests/test_dbpedia_samething.py
nifconverter/tests/test_dbpedia_sparql.py
nifconverter/tests/test_translator.py
nifconverter/tests/test_utils.py
nifconverter-0.2.2.dist-info/METADATA
nifconverter-0.2.2.dist-info/WHEEL
nifconverter-0.2.2.dist-info/entry_points.txt
nifconverter-0.2.2.dist-info/top_level.txt
nifconverter-0.2.2.dist-info/RECORD
