Metadata-Version: 2.1
Name: nifconverter
Version: 0.2.2
Summary: A tool to convert NIF files across identifier schemes (DBpedia, Wikidata, ...)
Home-page: https://github.com/wetneb/nifconverter
Author: Antonin Delpeuch
Author-email: antonin@delpeuch.eu
License: MIT
Keywords: NIF NLP formats NER RDF Wikidata DBpedia
Platform: UNKNOWN
Classifier: Development Status :: 3 - Alpha
Classifier: Intended Audience :: Developers
Classifier: Topic :: Scientific/Engineering :: Information Analysis
Classifier: License :: OSI Approved :: MIT License
Classifier: Programming Language :: Python :: 2
Classifier: Programming Language :: Python :: 2.7
Classifier: Programming Language :: Python :: 3
Classifier: Programming Language :: Python :: 3.3
Classifier: Programming Language :: Python :: 3.4
Classifier: Programming Language :: Python :: 3.5
Classifier: Programming Language :: Python :: 3.6
Classifier: Programming Language :: Python :: 3.7
Requires-Dist: pynif
Requires-Dist: requests
Requires-Dist: click
Provides-Extra: dev
Requires-Dist: check-manifest ; extra == 'dev'
Provides-Extra: test
Requires-Dist: coverage ; extra == 'test'
Requires-Dist: pytest ; extra == 'test'
Requires-Dist: requests-mock ; extra == 'test'
